dokos/VERSION
dokos/__init__.py
dokos/__main__.py
dokos-1.0.6.dist-info/METADATA
dokos-1.0.6.dist-info/WHEEL
dokos-1.0.6.dist-info/entry_points.txt
dokos-1.0.6.dist-info/licenses/LICENSE
dokos-1.0.6.dist-info/RECORD
