Metadata-Version: 2.1
Name: Dokos
Version: 1.0.6
Summary: HTTP login cracker
Project-URL: Homepage, https://gitlab.cylab.be/cylab/dokos
Project-URL: Bug Tracker, https://gitlab.cylab.be/cylab/dokos/-/issues
Author-email: Thibault Debatty <t.debatty@cylab.be>
License-File: LICENSE
Classifier: License :: OSI Approved :: MIT License
Classifier: Operating System :: OS Independent
Classifier: Programming Language :: Python :: 3
Requires-Python: >=3.7
Requires-Dist: validators
